setup_common/__init__.py
setup_common/aws.py
setup_common/db.py
setup_common/email.py
setup_common/jira.py
setup_common/json.py
setup_common/testrail.py
utils/__init__.py
utils/utils.py
monika_pytest_framework-0.1.0.dist-info/METADATA
monika_pytest_framework-0.1.0.dist-info/WHEEL
monika_pytest_framework-0.1.0.dist-info/top_level.txt
monika_pytest_framework-0.1.0.dist-info/RECORD
