Metadata-Version: 2.4
Name: monika-pytest_framework
Version: 0.1.0
Summary: pytest framework
